scikit_obliquetree/BUTIF.py
scikit_obliquetree/CO2.py
scikit_obliquetree/GradientBoosting.py
scikit_obliquetree/HHCART.py
scikit_obliquetree/__init__.py
scikit_obliquetree/__main__.py
scikit_obliquetree/basic_functions.py
scikit_obliquetree/example.py
scikit_obliquetree/py.typed
scikit_obliquetree/segmentor.py
scikit_obliquetree-0.1.4.dist-info/entry_points.txt
scikit_obliquetree-0.1.4.dist-info/LICENSE
scikit_obliquetree-0.1.4.dist-info/WHEEL
scikit_obliquetree-0.1.4.dist-info/METADATA
scikit_obliquetree-0.1.4.dist-info/RECORD
