Metadata-Version: 2.1
Name: scikit-obliquetree
Version: 0.1.4
Summary: Oblique Decision Tree in Python
Home-page: https://github.com/zhenlingcn/scikit-obliquetree
License: Apache Software License 2.0
Author: ECNU
Author-email: zhenlingcn@foxmail.com
Requires-Python: >=3.6,<4.0
Classifier: Development Status :: 3 - Alpha
Classifier: Intended Audience :: Developers
Classifier: License :: Other/Proprietary License
Classifier: Operating System :: OS Independent
Classifier: Programming Language :: Python :: 3
Classifier: Programming Language :: Python :: 3.6
Classifier: Programming Language :: Python :: 3.7
Classifier: Programming Language :: Python :: 3.8
Classifier: Programming Language :: Python :: 3.9
Classifier: Topic :: Software Development :: Libraries :: Python Modules
Requires-Dist: importlib_metadata (>=1.6.0,<2.0.0); python_version < "3.8"
Requires-Dist: rich (>=9.8.2,<10.0.0)
Requires-Dist: typer[all] (>=0.3.2,<0.4.0)
Project-URL: Repository, https://github.com/zhenlingcn/scikit-obliquetree
